zfs/__init__.pyi
zfs/replicate/__init__.py
zfs/replicate/cli/__init__.py
zfs/replicate/cli/click.py
zfs/replicate/cli/main.py
zfs/replicate/compress/__init__.py
zfs/replicate/compress/command.py
zfs/replicate/compress/type.py
zfs/replicate/error.py
zfs/replicate/filesystem/__init__.py
zfs/replicate/filesystem/create.py
zfs/replicate/filesystem/destroy.py
zfs/replicate/filesystem/list.py
zfs/replicate/filesystem/type.py
zfs/replicate/list.py
zfs/replicate/optional.py
zfs/replicate/snapshot/__init__.py
zfs/replicate/snapshot/destroy.py
zfs/replicate/snapshot/list.py
zfs/replicate/snapshot/send.py
zfs/replicate/snapshot/type.py
zfs/replicate/ssh/__init__.py
zfs/replicate/ssh/cipher.py
zfs/replicate/ssh/command.py
zfs/replicate/subprocess.py
zfs/replicate/task/__init__.py
zfs/replicate/task/execute.py
zfs/replicate/task/generate.py
zfs/replicate/task/report.py
zfs/replicate/task/type.py
zfs_replicate-4.0.0.dist-info/LICENSE
zfs_replicate-4.0.0.dist-info/METADATA
zfs_replicate-4.0.0.dist-info/WHEEL
zfs_replicate-4.0.0.dist-info/entry_points.txt
zfs_replicate-4.0.0.dist-info/RECORD
