Metadata-Version: 2.1
Name: zfs-replicate
Version: 4.0.0
Summary: ZFS Snapshot Replicator
Home-page: https://github.com/alunduil/zfs-replicate
License: BSD-2-Clause
Keywords: zfs,replication,backup,remote
Author: Alex Brandt
Author-email: alunduil@gmail.com
Requires-Python: >=3.8.0,<4.0.0
Classifier: Development Status :: 5 - Production/Stable
Classifier: Environment :: Console
Classifier: Intended Audience :: End Users/Desktop
Classifier: Intended Audience :: System Administrators
Classifier: License :: OSI Approved :: BSD License
Classifier: Natural Language :: English
Classifier: Operating System :: POSIX :: Linux
Classifier: Programming Language :: Python
Classifier: Programming Language :: Python :: 3
Classifier: Programming Language :: Python :: 3.8
Classifier: Programming Language :: Python :: 3.9
Classifier: Programming Language :: Python :: 3.10
Classifier: Programming Language :: Python :: 3.11
Classifier: Programming Language :: Python :: 3.12
Classifier: Programming Language :: Python :: 3.13
Classifier: Programming Language :: Python :: 3 :: Only
Classifier: Topic :: System
Classifier: Topic :: System :: Archiving
Classifier: Topic :: System :: Filesystems
Requires-Dist: click (>=8.1.3,<9.0.0)
Project-URL: Repository, https://github.com/alunduil/zfs-replicate
